pydroid/__init__.py
pydroid/ocroid.py
pydroid/pydroid.py
pydroid-0.1.4.data/scripts/sample_test_script.py
pydroid-0.1.4.dist-info/LICENSE
pydroid-0.1.4.dist-info/METADATA
pydroid-0.1.4.dist-info/WHEEL
pydroid-0.1.4.dist-info/top_level.txt
pydroid-0.1.4.dist-info/RECORD
