Metadata-Version: 2.1
Name: pydroid
Version: 0.1.4
Summary: An Android Device Automation Framework package to control ADB using shell
Home-page: https://github.com/nandal/pydroid
Author: Sandeep Nandal
Author-email: sandeep@nandal.in
License: UNKNOWN
Keywords: pydroid android automation adb tools
Platform: UNKNOWN
Classifier: Programming Language :: Python :: 3
Classifier: License :: OSI Approved :: MIT License
Classifier: Operating System :: OS Independent
Requires-Dist: pathlib
